lorem/__init__.py
lorem/lorem.py
lorem/tests/__init__.py
lorem/tests/test_lorem.py
python_lorem_ipsum-2.0.0.dist-info/LICENSE
python_lorem_ipsum-2.0.0.dist-info/METADATA
python_lorem_ipsum-2.0.0.dist-info/WHEEL
python_lorem_ipsum-2.0.0.dist-info/top_level.txt
python_lorem_ipsum-2.0.0.dist-info/RECORD
