Metadata-Version: 2.1
Name: python-lorem-ipsum
Version: 2.0.0
Summary: Generate Lorem Ipsum Text
Home-page: https://github.com/adambirds/python-lorem-ipsum
Author: Adam Birds
Author-email: adam.birds@adbwebdesigns.co.uk
License: BSD-3-Clause
Project-URL: Bug Tracker, https://github.com/adambirds/python-lorem-ipsum/issues
Classifier: License :: OSI Approved :: GNU General Public License v3 (GPLv3)
Classifier: Programming Language :: Python
Classifier: Programming Language :: Python :: 3
Classifier: Programming Language :: Python :: 3.6
Classifier: Programming Language :: Python :: 3.7
Classifier: Programming Language :: Python :: 3.8
Classifier: Programming Language :: Python :: 3.9
Classifier: Programming Language :: Python :: 3.10
Classifier: Operating System :: OS Independent
Requires-Python: >=3.6
License-File: LICENSE
